[
    {
        "title": "Use Cases",
        "words": [
            "UI Design",
            "UX Design",
            "Prototyping",
            "UI Design",
            "UX Design",
            "Prototyping"
        ]
    },
    {
        "title": "Explore",
        "words": [
            "Figma",
            "Customers",
            "Why I Love Figma",
            "Figma",
            "Customers",
            "Why I Love Figma"
        ]
    },
    {
        "title": "Resources",
        "words": [
            "Community Resources Hub",
            "Support",
            "Education",
            "Community Resources Hub",
            "Support",
            "Education"
        ]
    }
]